targeting_platform/__init__.py
targeting_platform/platform.py
targeting_platform/platform_dv360.py
targeting_platform/platform_meta.py
targeting_platform/platform_ttd.py
targeting_platform/utils_cache.py
targeting_platform/utils_common.py
targeting_platform-0.3.4.dist-info/LICENSE
targeting_platform-0.3.4.dist-info/METADATA
targeting_platform-0.3.4.dist-info/WHEEL
targeting_platform-0.3.4.dist-info/top_level.txt
targeting_platform-0.3.4.dist-info/RECORD
