Metadata-Version: 2.1
Name: targeting_platform
Version: 0.3.4
Summary: Set targeting in diffrent advertisment platforms.
Author-email: Siarhei Ivanou <sinusu@gmail.com>
Maintainer-email: Siarhei Ivanou <sinusu@gmail.com>
License: GPL-3.0
Project-URL: Homepage, https://gitlab.com/dsp6802915/targeting_platform
Project-URL: Documentation, https://targeting-platform-dsp6802915-32831787e4a994dfa12bcd1ddb4f2c051.gitlab.io/
Keywords: dsp,google dv360,meta marketing api,the trade desk
Classifier: Programming Language :: Python :: 3.11
Classifier: License :: OSI Approved :: GNU General Public License v3 (GPLv3)
Classifier: Intended Audience :: Developers
Classifier: Operating System :: OS Independent
License-File: LICENSE
Requires-Dist: requests ==2.31.0
Requires-Dist: typing-extensions ==4.11.0
Requires-Dist: redis[hiredis] ==5.0.3
Requires-Dist: facebook-business ==20.0.0
Requires-Dist: google-api-python-client ==2.126.0
Requires-Dist: pytz ==2024.1
Requires-Dist: h3 ==3.7.6
Requires-Dist: pandas ==2.2.2
Requires-Dist: numpy ==1.26.4
Provides-Extra: dev
Requires-Dist: coverage ; extra == 'dev'
Requires-Dist: mypy ; extra == 'dev'
Requires-Dist: pytest ; extra == 'dev'
Requires-Dist: ruff ; extra == 'dev'
